mock_decorators/__init__.py
mock_decorators/attribute_mock.py
mock_decorators/class_mock.py
mock_decorators/dict_mock.py
mock_decorators/function_mock.py
mock_decorators/mock_sys_output.py
mock_decorators/object_mock.py
mock_decorators/utils.py
mock_decorators-1.1.1.dist-info/DESCRIPTION.rst
mock_decorators-1.1.1.dist-info/METADATA
mock_decorators-1.1.1.dist-info/RECORD
mock_decorators-1.1.1.dist-info/WHEEL
mock_decorators-1.1.1.dist-info/metadata.json
mock_decorators-1.1.1.dist-info/top_level.txt
