Metadata-Version: 2.0
Name: mock-decorators
Version: 1.1.1
Summary: Mock library using python decorators
Home-page: https://github.com/fhuertas/mock_decorators
Author: Francisco Huertas
Author-email: pacohuertas@gmail.com
License: Apache2
Download-URL: https://github.com/fhuertas/mock_decorators/tarball/1.1.1
Platform: UNKNOWN
Classifier: Development Status :: 5 - Production/Stable
Classifier: Topic :: Utilities
Classifier: License :: OSI Approved :: Apache Software License
Classifier: Programming Language :: Python :: 2
Classifier: Programming Language :: Python :: 2.7
Classifier: Programming Language :: Python :: 3
Classifier: Programming Language :: Python :: 3.4
Classifier: Programming Language :: Python :: 3.5
